RISCV/ProgramCounter.v

module ProgramCounter
       #( parameter WIDTH = 32)
       (
        input clk,reset,
        input [WIDTH-1:0] pc_in,
        output [WIDTH-1:0] pc_out
       );


    reg [WIDTH-1:0] temp;

    assign pc_out = temp;

    always @(posedge clk ) begin
        temp = reset ? 32'b0 : pc_in;
    end


endmodule

DataPath/ArchitecturalStateRegisters/ProgramCounter/tb.v
`timescale 1ns/1ps
`include "ProgramCounter.v"

module tb;

parameter WID = 32 ;

reg [WID-1:0] pc_in;
reg clk,reset;
wire [WID-1:0] pc_out;

ProgramCounter #(.WIDTH(32)) dut(
    .clk(clk),
    .reset(reset),
    .pc_in(pc_in),
    .pc_out(pc_out)
);

always #5clk =  ~clk;

initial begin
    $dumpfile("tb.vcd");
    $dumpvars(0,tb);
end

initial begin
    clk = 0;
    reset = 1;
    #10 reset = 0;

    pc_in = 32'b0;
    #10 pc_in = 32'b1;  
    #10 pc_in = 32'b10;
    #10 pc_in = 32'b11;
    #10 pc_in = 32'b100;
    #2 reset = 1;
    #10 reset = 0;
    #10 $finish;

end



endmodule

DataPath/ArchitecturalStateRegisters/ProgramCounter/tb.vcd
$date
	Wed Feb 26 14:02:54 2025
$end
$version
	Icarus Verilog
$end
$timescale
	1ps
$end
$scope module tb $end
$var wire 32 ! pc_out [31:0] $end
$var parameter 32 " WID $end
$var reg 1 # clk $end
$var reg 32 $ pc_in [31:0] $end
$var reg 1 % reset $end
$scope module dut $end
$var wire 1 # clk $end
$var wire 32 & pc_in [31:0] $end
$var wire 32 ' pc_out [31:0] $end
$var wire 1 % reset $end
$var parameter 32 ( WIDTH $end
$var reg 32 ) temp [31:0] $end
$upscope $end
$upscope $end
$enddefinitions $end
$comment Show the parameter values. $end
$dumpall
b100000 (
b100000 "
$end
#0
$dumpvars
bx )
bx '
bx &
1%
bx $
0#
bx !
$end
#5000
b0 !
b0 '
b0 )
1#
#10000
0#
b0 $
b0 &
0%
#15000
1#
#20000
0#
b1 $
b1 &
#25000
b1 !
b1 '
b1 )
1#
#30000
0#
b10 $
b10 &
#35000
b10 !
b10 '
b10 )
1#
#40000
0#
b11 $
b11 &
#45000
b11 !
b11 '
b11 )
1#
#50000
0#
b100 $
b100 &
#52000
1%
#55000
b0 !
b0 '
b0 )
1#
#60000
0#
#62000
0%
#65000
b100 !
b100 '
b100 )
1#
