RISCV/Adder.v
module Adder #(parameter WIDTH = 32)(
    
    input [WIDTH-1:0]SrcA,
    input [WIDTH-1:0]SrcB,
    output [WIDTH-1:0]Result

);

    assign Result = SrcA + SrcB;


endmodule

DataPath/Adders/tb.v
`timescale 1ns / 1ps
`include "Adder.v"

module tb;

    reg [31:0] A,B;
    wire [31:0] Sum;

    integer i;

    Adder #(.WIDTH(32)) dut(
        .SrcA(A),
        .SrcB(B),
        .Result(Sum)
    );

    initial begin

        $dumpfile("tb.vcd");
        $dumpvars(0, tb);


    end

    initial begin

        for(i = 0 ; i < 20 ; i = i +1)
        begin
            A = $random%300;
            B = $random%300;
            #5;
        end

    end


endmodule

DataPath/Adders/tb.vcd
$date
	Thu Mar 13 18:28:42 2025
$end
$version
	Icarus Verilog
$end
$timescale
	1ps
$end
$scope module tb $end
$var wire 32 ! Sum [31:0] $end
$var reg 32 " A [31:0] $end
$var reg 32 # B [31:0] $end
$var integer 32 $ i [31:0] $end
$scope module dut $end
$var wire 32 % SrcA [31:0] $end
$var wire 32 & SrcB [31:0] $end
$var wire 32 ' Result [31:0] $end
$var parameter 32 ( WIDTH $end
$upscope $end
$upscope $end
$enddefinitions $end
$comment Show the parameter values. $end
$dumpall
b100000 (
$end
#0
$dumpvars
b110001 '
b11111111111111111111111100111001 &
b11111000 %
b0 $
b11111111111111111111111100111001 #
b11111000 "
b110001 !
$end
#5000
b11111111111111111111111100101111 #
b11111111111111111111111100101111 &
b11111111111111111111111100001000 !
b11111111111111111111111100001000 '
b11111111111111111111111111011001 "
b11111111111111111111111111011001 %
b1 $
#10000
b100000001 #
b100000001 &
b100111010 !
b100111010 '
b111001 "
b111001 %
b10 $
#15000
b11111111111111111111111110001110 #
b11111111111111111111111110001110 &
b11111111111111111111111101000111 !
b11111111111111111111111101000111 '
b11111111111111111111111110111001 "
b11111111111111111111111110111001 %
b11 $
#20000
b11100101 #
b11100101 &
b111101010 !
b111101010 '
b100000101 "
b100000101 %
b100 $
#25000
b11000101 #
b11000101 &
b11010111 !
b11010111 '
b10010 "
b10010 %
b101 $
#30000
b1110000 #
b1110000 &
b11110001 !
b11110001 '
b10000001 "
b10000001 %
b110 $
#35000
b11111111111111111111111110111010 #
b11111111111111111111111110111010 &
b11011011 !
b11011011 '
b100100001 "
b100100001 %
b111 $
#40000
b11111111111111111111111011101110 #
b11111111111111111111111011101110 &
b11111111111111111111111010001011 !
b11111111111111111111111010001011 '
b11111111111111111111111110011101 "
b11111111111111111111111110011101 %
b1000 $
#45000
b11111111111111111111111100001111 #
b11111111111111111111111100001111 &
b101100 !
b101100 '
b100011101 "
b100011101 %
b1001 $
#50000
b100111 #
b100111 &
b100101 !
b100101 '
b11111111111111111111111111111110 "
b11111111111111111111111111111110 %
b1010 $
#55000
b11111111111111111111111111010010 #
b11111111111111111111111111010010 &
b10001100 !
b10001100 '
b10111010 "
b10111010 %
b1011 $
#60000
b11111111111111111111111100001101 #
b11111111111111111111111100001101 &
b11111111111111111111111000101001 !
b11111111111111111111111000101001 '
b11111111111111111111111100011100 "
b11111111111111111111111100011100 %
b1100 $
#65000
b11111111111111111111111100110101 #
b11111111111111111111111100110101 &
b1010001 !
b1010001 '
b100011100 "
b100011100 %
b1101 $
#70000
b11111111111111111111111100110001 #
b11111111111111111111111100110001 &
b11111111111111111111111000100110 !
b11111111111111111111111000100110 '
b11111111111111111111111011110101 "
b11111111111111111111111011110101 %
b1110 $
#75000
b10111110 #
b10111110 &
b11111111111111111111111110101101 !
b11111111111111111111111110101101 '
b11111111111111111111111011101111 "
b11111111111111111111111011101111 %
b1111 $
#80000
b10001000 #
b10001000 &
b1000100 !
b1000100 '
b11111111111111111111111110111100 "
b11111111111111111111111110111100 %
b10000 $
#85000
b11111111111111111111111101010001 #
b11111111111111111111111101010001 &
b11111111111111111111111111000011 !
b11111111111111111111111111000011 '
b1110010 "
b1110010 %
b10001 $
#90000
b11111111111111111111111011110111 #
b11111111111111111111111011110111 &
b11111111111111111111110111100101 !
b11111111111111111111110111100101 '
b11111111111111111111111011101110 "
b11111111111111111111111011101110 %
b10010 $
#95000
b11111111111111111111111111110011 #
b11111111111111111111111111110011 &
b11111111111111111111111101101100 !
b11111111111111111111111101101100 '
b11111111111111111111111101111001 "
b11111111111111111111111101111001 %
b10011 $
#100000
b10100 $
