DataPath/ArchitecturalStateRegisters/RegisterFile/RegisterFile.v
module RegisterFile
    #(parameter ADDR_WIDTH = 5,parameter DATA_WIDTH = 32)
    (input [ADDR_WIDTH-1:0]A1,A2,A3,
     input [DATA_WIDTH-1:0]WD3,
     input CLK,
     input WE3,
     output [DATA_WIDTH-1:0]RD1,RD2 );
     integer i;

     reg [DATA_WIDTH-1:0] regfile[2**ADDR_WIDTH-1:0];


     assign RD1 = regfile[A1];
     assign RD2 = regfile[A2];

     always @(posedge CLK ) regfile[0] <= 0;   // X0 is always 0

     always @(posedge CLK) begin
            if(WE3) regfile[A3] <= WD3;
     end




endmodule

DataPath/ArchitecturalStateRegisters/RegisterFile/tb.v
`timescale 1ns/1ps
`include "RegisterFile.v"

module tb;

    parameter ADDR_WIDTH = 5;
    parameter DATA_WIDTH = 32;

    reg [ADDR_WIDTH-1:0] A1,A2,A3;
    reg [DATA_WIDTH-1:0] WD3;
    reg CLK,WE3;
    wire [DATA_WIDTH-1:0] RD1,RD2;

    integer i;

    RegisterFile #(ADDR_WIDTH,DATA_WIDTH) RF1(.A1(A1),.A2(A2),.A3(A3),.WD3(WD3),.CLK(CLK),.WE3(WE3),.RD1(RD1),.RD2(RD2));

    always #5 CLK = ~CLK;

    initial begin
        $dumpfile("tb.vcd");
        $dumpvars(0,tb);
        #1000 $finish;
    end

    initial begin   // Initialise Register File

        CLK = 0;
        WE3 = 1;

        for(i = 0 ; i < DATA_WIDTH ; i = i + 1) begin
            
            A3 = i;
            WD3 =i;
        #10;
        end
        WE3 = 0;

        for(i = 0 ; i < DATA_WIDTH ; i = i + 1) begin
        #4 A1 = $urandom%32;
        #4 A2 = $urandom%32;
      
        end

       


    end



endmodule

DataPath/ArchitecturalStateRegisters/RegisterFile/tb.vcd
$date
	Wed Feb 26 17:11:03 2025
$end
$version
	Icarus Verilog
$end
$timescale
	1ps
$end
$scope module tb $end
$var wire 32 ! RD2 [31:0] $end
$var wire 32 " RD1 [31:0] $end
$var parameter 32 # ADDR_WIDTH $end
$var parameter 32 $ DATA_WIDTH $end
$var reg 5 % A1 [4:0] $end
$var reg 5 & A2 [4:0] $end
$var reg 5 ' A3 [4:0] $end
$var reg 1 ( CLK $end
$var reg 32 ) WD3 [31:0] $end
$var reg 1 * WE3 $end
$var integer 32 + i [31:0] $end
$scope module RF1 $end
$var wire 5 , A1 [4:0] $end
$var wire 5 - A2 [4:0] $end
$var wire 5 . A3 [4:0] $end
$var wire 1 ( CLK $end
$var wire 32 / RD1 [31:0] $end
$var wire 32 0 RD2 [31:0] $end
$var wire 32 1 WD3 [31:0] $end
$var wire 1 * WE3 $end
$var parameter 32 2 ADDR_WIDTH $end
$var parameter 32 3 DATA_WIDTH $end
$upscope $end
$upscope $end
$enddefinitions $end
$comment Show the parameter values. $end
$dumpall
b100000 3
b101 2
b100000 $
b101 #
$end
#0
$dumpvars
b0 1
bx 0
bx /
b0 .
bx -
bx ,
b0 +
1*
b0 )
0(
b0 '
bx &
bx %
bx "
bx !
$end
#5000
1(
#10000
0(
b1 )
b1 1
b1 '
b1 .
b1 +
#15000
1(
#20000
0(
b10 )
b10 1
b10 '
b10 .
b10 +
#25000
1(
#30000
0(
b11 )
b11 1
b11 '
b11 .
b11 +
#35000
1(
#40000
0(
b100 )
b100 1
b100 '
b100 .
b100 +
#45000
1(
#50000
0(
b101 )
b101 1
b101 '
b101 .
b101 +
#55000
1(
#60000
0(
b110 )
b110 1
b110 '
b110 .
b110 +
#65000
1(
#70000
0(
b111 )
b111 1
b111 '
b111 .
b111 +
#75000
1(
#80000
0(
b1000 )
b1000 1
b1000 '
b1000 .
b1000 +
#85000
1(
#90000
0(
b1001 )
b1001 1
b1001 '
b1001 .
b1001 +
#95000
1(
#100000
0(
b1010 )
b1010 1
b1010 '
b1010 .
b1010 +
#105000
1(
#110000
0(
b1011 )
b1011 1
b1011 '
b1011 .
b1011 +
#115000
1(
#120000
0(
b1100 )
b1100 1
b1100 '
b1100 .
b1100 +
#125000
1(
#130000
0(
b1101 )
b1101 1
b1101 '
b1101 .
b1101 +
#135000
1(
#140000
0(
b1110 )
b1110 1
b1110 '
b1110 .
b1110 +
#145000
1(
#150000
0(
b1111 )
b1111 1
b1111 '
b1111 .
b1111 +
#155000
1(
#160000
0(
b10000 )
b10000 1
b10000 '
b10000 .
b10000 +
#165000
1(
#170000
0(
b10001 )
b10001 1
b10001 '
b10001 .
b10001 +
#175000
1(
#180000
0(
b10010 )
b10010 1
b10010 '
b10010 .
b10010 +
#185000
1(
#190000
0(
b10011 )
b10011 1
b10011 '
b10011 .
b10011 +
#195000
1(
#200000
0(
b10100 )
b10100 1
b10100 '
b10100 .
b10100 +
#205000
1(
#210000
0(
b10101 )
b10101 1
b10101 '
b10101 .
b10101 +
#215000
1(
#220000
0(
b10110 )
b10110 1
b10110 '
b10110 .
b10110 +
#225000
1(
#230000
0(
b10111 )
b10111 1
b10111 '
b10111 .
b10111 +
#235000
1(
#240000
0(
b11000 )
b11000 1
b11000 '
b11000 .
b11000 +
#245000
1(
#250000
0(
b11001 )
b11001 1
b11001 '
b11001 .
b11001 +
#255000
1(
#260000
0(
b11010 )
b11010 1
b11010 '
b11010 .
b11010 +
#265000
1(
#270000
0(
b11011 )
b11011 1
b11011 '
b11011 .
b11011 +
#275000
1(
#280000
0(
b11100 )
b11100 1
b11100 '
b11100 .
b11100 +
#285000
1(
#290000
0(
b11101 )
b11101 1
b11101 '
b11101 .
b11101 +
#295000
1(
#300000
0(
b11110 )
b11110 1
b11110 '
b11110 .
b11110 +
#305000
1(
#310000
0(
b11111 )
b11111 1
b11111 '
b11111 .
b11111 +
#315000
1(
#320000
0(
0*
b0 +
#324000
b100 "
b100 /
b100 %
b100 ,
#325000
1(
#328000
b1 +
b1 !
b1 0
b1 &
b1 -
#330000
0(
#332000
b1001 "
b1001 /
b1001 %
b1001 ,
#335000
1(
#336000
b10 +
b11 !
b11 0
b11 &
b11 -
#340000
b1101 "
b1101 /
b1101 %
b1101 ,
0(
#344000
b11 +
b1101 !
b1101 0
b1101 &
b1101 -
#345000
1(
#348000
b101 "
b101 /
b101 %
b101 ,
#350000
0(
#352000
b100 +
b10010 !
b10010 0
b10010 &
b10010 -
#355000
1(
#356000
b1 "
b1 /
b1 %
b1 ,
#360000
b101 +
b1101 !
b1101 0
b1101 &
b1101 -
0(
#364000
b10110 "
b10110 /
b10110 %
b10110 ,
#365000
1(
#368000
b110 +
b11101 !
b11101 0
b11101 &
b11101 -
#370000
0(
#372000
b1101 "
b1101 /
b1101 %
b1101 ,
#375000
1(
#376000
b111 +
b1100 !
b1100 0
b1100 &
b1100 -
#380000
b11001 "
b11001 /
b11001 %
b11001 ,
0(
#384000
b1000 +
b110 !
b110 0
b110 &
b110 -
#385000
1(
#388000
b101 "
b101 /
b101 %
b101 ,
#390000
0(
#392000
b1001 +
b1010 !
b1010 0
b1010 &
b1010 -
#395000
1(
#400000
b1010 +
b10111 !
b10111 0
b10111 &
b10111 -
0(
#404000
b10010 "
b10010 /
b10010 %
b10010 ,
#405000
1(
#408000
b1011 +
b1111 !
b1111 0
b1111 &
b1111 -
#410000
0(
#415000
1(
#416000
b1100 +
b1110 !
b1110 0
b1110 &
b1110 -
#420000
b1000 "
b1000 /
b1000 %
b1000 ,
0(
#424000
b1101 +
b101 !
b101 0
b101 &
b101 -
#425000
1(
#428000
b11100 "
b11100 /
b11100 %
b11100 ,
#430000
0(
#432000
b1110 +
b11101 !
b11101 0
b11101 &
b11101 -
#435000
1(
#436000
b1101 "
b1101 /
b1101 %
b1101 ,
#440000
b1111 +
b101 !
b101 0
b101 &
b101 -
0(
#444000
b11 "
b11 /
b11 %
b11 ,
#445000
1(
#448000
b10000 +
b1010 !
b1010 0
b1010 &
b1010 -
#450000
0(
#452000
b0 "
b0 /
b0 %
b0 ,
#455000
1(
#456000
b10001 +
b0 !
b0 0
b0 &
b0 -
#460000
b1010 "
b1010 /
b1010 %
b1010 ,
0(
#464000
b10010 +
b11101 !
b11101 0
b11101 &
b11101 -
#465000
1(
#468000
b10110 "
b10110 /
b10110 %
b10110 ,
#470000
0(
#472000
b10011 +
b10011 !
b10011 0
b10011 &
b10011 -
#475000
1(
#476000
b1101 "
b1101 /
b1101 %
b1101 ,
#480000
b10100 +
0(
#484000
b1011 "
b1011 /
b1011 %
b1011 ,
#485000
1(
#488000
b10101 +
b10101 !
b10101 0
b10101 &
b10101 -
#490000
0(
#492000
b10 "
b10 /
b10 %
b10 ,
#495000
1(
#496000
b10110 +
b1110 !
b1110 0
b1110 &
b1110 -
#500000
b11101 "
b11101 /
b11101 %
b11101 ,
0(
#504000
b10111 +
b1111 !
b1111 0
b1111 &
b1111 -
#505000
1(
#508000
b11 "
b11 /
b11 %
b11 ,
#510000
0(
#512000
b11000 +
b1010 !
b1010 0
b1010 &
b1010 -
#515000
1(
#516000
b1010 "
b1010 /
b1010 %
b1010 ,
#520000
b11001 +
b11100 !
b11100 0
b11100 &
b11100 -
0(
#524000
b10010 "
b10010 /
b10010 %
b10010 ,
#525000
1(
#528000
b11010 +
b1010 !
b1010 0
b1010 &
b1010 -
#530000
0(
#532000
b1 "
b1 /
b1 %
b1 ,
#535000
1(
#536000
b11011 +
b11000 !
b11000 0
b11000 &
b11000 -
#540000
b11000 "
b11000 /
b11000 %
b11000 ,
0(
#544000
b11100 +
b1001 !
b1001 0
b1001 &
b1001 -
#545000
1(
#548000
b1011 "
b1011 /
b1011 %
b1011 ,
#550000
0(
#552000
b11101 +
b10110 !
b10110 0
b10110 &
b10110 -
#555000
1(
#556000
b110 "
b110 /
b110 %
b110 ,
#560000
b11110 +
b1110 !
b1110 0
b1110 &
b1110 -
0(
#564000
b11100 "
b11100 /
b11100 %
b11100 ,
#565000
1(
#568000
b11111 +
b1010 !
b1010 0
b1010 &
b1010 -
#570000
0(
#572000
b1011 "
b1011 /
b1011 %
b1011 ,
#575000
1(
#576000
b100000 +
b10001 !
b10001 0
b10001 &
b10001 -
