RISCV/DataMemory.v

module DataMemory
    #(parameter Width = 32 )
    (input [Width-1:0]A,
     input [Width-1:0]WD,
     input CLK,WE,
     output [Width-1:0]RD
    );

    reg [7:0] mem[255:0]; // Little Endian - Less memory is chosen for simulation

    always @(posedge CLK)
    begin
        if(WE)
            {mem[A+3],mem[A+2],mem[A+1],mem[A]} <= WD;
    end

    assign RD =  A > 255 ? 0 : {mem[A+3],mem[A+2],mem[A+1],mem[A]};


endmodule

DataPath/DataMemory/tb.v
`include "DataMemory.v"
`timescale 1ns/1ps

module tb;
    reg [31:0] A,WD;
    reg CLK,WE;
    wire [31:0] RD;
    integer i;

    DataMemory #(32) DM(.A(A),.WD(WD),.CLK(CLK),.WE(WE),.RD(RD));

    always #5 CLK = ~CLK;

    initial begin
        CLK = 0;
        $dumpfile("tb.vcd");
        $dumpvars(0,tb);
        #500 $finish;
    end

    initial
    begin
        #1 ;
        WE = 1;
        for(i = 0; i < 32 ; i = i + 1 )
        begin
            
            A = i*4;
            WD = $urandom;
            #10;
            $display("A = %d, WD = %d, Memory Value = %d",A,WD,{DM.mem[A+3],DM.mem[A+2],DM.mem[A+1],DM.mem[A]});
        end


        WE = 0;
        #1;
        for(i = 0; i < 36 ; i = i + 1 )
        begin
            
            A = i*4;
            #10;
        end
    end

endmodule

DataPath/DataMemory/tb.vcd
$date
	Thu Mar 13 14:34:56 2025
$end
$version
	Icarus Verilog
$end
$timescale
	1ps
$end
$scope module tb $end
$var wire 32 ! RD [31:0] $end
$var reg 32 " A [31:0] $end
$var reg 1 # CLK $end
$var reg 32 $ WD [31:0] $end
$var reg 1 % WE $end
$var integer 32 & i [31:0] $end
$scope module DM $end
$var wire 32 ' A [31:0] $end
$var wire 1 # CLK $end
$var wire 32 ( WD [31:0] $end
$var wire 1 % WE $end
$var wire 32 ) RD [31:0] $end
$var parameter 32 * Width $end
$upscope $end
$upscope $end
$enddefinitions $end
$comment Show the parameter values. $end
$dumpall
b100000 *
$end
#0
$dumpvars
bx )
bx (
bx '
bx &
x%
bx $
0#
bx "
bx !
$end
#1000
b10010010000101010011010100100100 $
b10010010000101010011010100100100 (
b0 "
b0 '
b0 &
1%
#5000
b10010010000101010011010100100100 !
b10010010000101010011010100100100 )
1#
#10000
0#
#11000
bx !
bx )
b1000000100010010101111010000001 $
b1000000100010010101111010000001 (
b100 "
b100 '
b1 &
#15000
b1000000100010010101111010000001 !
b1000000100010010101111010000001 )
1#
#20000
0#
#21000
bx !
bx )
b100100001001101011000001001 $
b100100001001101011000001001 (
b1000 "
b1000 '
b10 &
#25000
b100100001001101011000001001 !
b100100001001101011000001001 )
1#
#30000
0#
#31000
bx !
bx )
b110001111100000101011001100011 $
b110001111100000101011001100011 (
b1100 "
b1100 '
b11 &
#35000
b110001111100000101011001100011 !
b110001111100000101011001100011 )
1#
#40000
0#
#41000
bx !
bx )
b10000110101110010111101100001101 $
b10000110101110010111101100001101 (
b10000 "
b10000 '
b100 &
#45000
b10000110101110010111101100001101 !
b10000110101110010111101100001101 )
1#
#50000
0#
#51000
bx !
bx )
b11000110110111111001100110001101 $
b11000110110111111001100110001101 (
b10100 "
b10100 '
b101 &
#55000
b11000110110111111001100110001101 !
b11000110110111111001100110001101 )
1#
#60000
0#
#61000
bx !
bx )
b110010110000101000010001100101 $
b110010110000101000010001100101 (
b11000 "
b11000 '
b110 &
#65000
b110010110000101000010001100101 !
b110010110000101000010001100101 )
1#
#70000
0#
#71000
bx !
bx )
b1001001101110101001000010010 $
b1001001101110101001000010010 (
b11100 "
b11100 '
b111 &
#75000
b1001001101110101001000010010 !
b1001001101110101001000010010 )
1#
#80000
0#
#81000
bx !
bx )
b10000000111100111110001100000001 $
b10000000111100111110001100000001 (
b100000 "
b100000 '
b1000 &
#85000
b10000000111100111110001100000001 !
b10000000111100111110001100000001 )
1#
#90000
0#
#91000
bx !
bx )
b10000110110101111100110100001101 $
b10000110110101111100110100001101 (
b100100 "
b100100 '
b1001 &
#95000
b10000110110101111100110100001101 !
b10000110110101111100110100001101 )
1#
#100000
0#
#101000
bx !
bx )
b10111011001000111111000101110110 $
b10111011001000111111000101110110 (
b101000 "
b101000 '
b1010 &
#105000
b10111011001000111111000101110110 !
b10111011001000111111000101110110 )
1#
#110000
0#
#111000
bx !
bx )
b10011110100011011100110100111101 $
b10011110100011011100110100111101 (
b101100 "
b101100 '
b1011 &
#115000
b10011110100011011100110100111101 !
b10011110100011011100110100111101 )
1#
#120000
0#
#121000
bx !
bx )
b11110110110101000101011111101101 $
b11110110110101000101011111101101 (
b110000 "
b110000 '
b1100 &
#125000
b11110110110101000101011111101101 !
b11110110110101000101011111101101 )
1#
#130000
0#
#131000
bx !
bx )
b11000110001011011111011110001100 $
b11000110001011011111011110001100 (
b110100 "
b110100 '
b1101 &
#135000
b11000110001011011111011110001100 !
b11000110001011011111011110001100 )
1#
#140000
0#
#141000
bx !
bx )
b11111100111111011110100111111001 $
b11111100111111011110100111111001 (
b111000 "
b111000 '
b1110 &
#145000
b11111100111111011110100111111001 !
b11111100111111011110100111111001 )
1#
#150000
0#
#151000
bx !
bx )
b1100011001101110010010011000110 $
b1100011001101110010010011000110 (
b111100 "
b111100 '
b1111 &
#155000
b1100011001101110010010011000110 !
b1100011001101110010010011000110 )
1#
#160000
0#
#161000
bx !
bx )
b1100010111101111000010011000101 $
b1100010111101111000010011000101 (
b1000000 "
b1000000 '
b10000 &
#165000
b1100010111101111000010011000101 !
b1100010111101111000010011000101 )
1#
#170000
0#
#171000
bx !
bx )
b1010101000100111101001010101010 $
b1010101000100111101001010101010 (
b1000100 "
b1000100 '
b10001 &
#175000
b1010101000100111101001010101010 !
b1010101000100111101001010101010 )
1#
#180000
0#
#181000
bx !
bx )
b11110010101011111111011111100101 $
b11110010101011111111011111100101 (
b1001000 "
b1001000 '
b10010 &
#185000
b11110010101011111111011111100101 !
b11110010101011111111011111100101 )
1#
#190000
0#
#191000
bx !
bx )
b111011110100100111001001110111 $
b111011110100100111001001110111 (
b1001100 "
b1001100 '
b10011 &
#195000
b111011110100100111001001110111 !
b111011110100100111001001110111 )
1#
#200000
0#
#201000
bx !
bx )
b1001001100101101011000010010 $
b1001001100101101011000010010 (
b1010000 "
b1010000 '
b10100 &
#205000
b1001001100101101011000010010 !
b1001001100101101011000010010 )
1#
#210000
0#
#211000
bx !
bx )
b11000111111011001101101110001111 $
b11000111111011001101101110001111 (
b1010100 "
b1010100 '
b10101 &
#215000
b11000111111011001101101110001111 !
b11000111111011001101101110001111 )
1#
#220000
0#
#221000
bx !
bx )
b11111001001100000110100111110010 $
b11111001001100000110100111110010 (
b1011000 "
b1011000 '
b10110 &
#225000
b11111001001100000110100111110010 !
b11111001001100000110100111110010 )
1#
#230000
0#
#231000
bx !
bx )
b1100111011101101001011011001110 $
b1100111011101101001011011001110 (
b1011100 "
b1011100 '
b10111 &
#235000
b1100111011101101001011011001110 !
b1100111011101101001011011001110 )
1#
#240000
0#
#241000
bx !
bx )
b1110100000000000111101011101000 $
b1110100000000000111101011101000 (
b1100000 "
b1100000 '
b11000 &
#245000
b1110100000000000111101011101000 !
b1110100000000000111101011101000 )
1#
#250000
0#
#251000
bx !
bx )
b1100010110010100100111011000101 $
b1100010110010100100111011000101 (
b1100100 "
b1100100 '
b11001 &
#255000
b1100010110010100100111011000101 !
b1100010110010100100111011000101 )
1#
#260000
0#
#261000
bx !
bx )
b10101110010110000100100101011100 $
b10101110010110000100100101011100 (
b1101000 "
b1101000 '
b11010 &
#265000
b10101110010110000100100101011100 !
b10101110010110000100100101011100 )
1#
#270000
0#
#271000
bx !
bx )
b1011110100011100010100010111101 $
b1011110100011100010100010111101 (
b1101100 "
b1101100 '
b11011 &
#275000
b1011110100011100010100010111101 !
b1011110100011100010100010111101 )
1#
#280000
0#
#281000
bx !
bx )
b10110101010110101100000101101 $
b10110101010110101100000101101 (
b1110000 "
b1110000 '
b11100 &
#285000
b10110101010110101100000101101 !
b10110101010110101100000101101 )
1#
#290000
0#
#291000
bx !
bx )
b110010101001110010011001100101 $
b110010101001110010011001100101 (
b1110100 "
b1110100 '
b11101 &
#295000
b110010101001110010011001100101 !
b110010101001110010011001100101 )
1#
#300000
0#
#301000
bx !
bx )
b110001111011110110001001100011 $
b110001111011110110001001100011 (
b1111000 "
b1111000 '
b11110 &
#305000
b110001111011110110001001100011 !
b110001111011110110001001100011 )
1#
#310000
0#
#311000
bx !
bx )
b10000101011100111000011100001010 $
b10000101011100111000011100001010 (
b1111100 "
b1111100 '
b11111 &
#315000
b10000101011100111000011100001010 !
b10000101011100111000011100001010 )
1#
#320000
0#
#321000
0%
b100000 &
#322000
b10010010000101010011010100100100 !
b10010010000101010011010100100100 )
b0 "
b0 '
b0 &
#325000
1#
#330000
0#
#332000
b1000000100010010101111010000001 !
b1000000100010010101111010000001 )
b100 "
b100 '
b1 &
#335000
1#
#340000
0#
#342000
b100100001001101011000001001 !
b100100001001101011000001001 )
b1000 "
b1000 '
b10 &
#345000
1#
#350000
0#
#352000
b110001111100000101011001100011 !
b110001111100000101011001100011 )
b1100 "
b1100 '
b11 &
#355000
1#
#360000
0#
#362000
b10000110101110010111101100001101 !
b10000110101110010111101100001101 )
b10000 "
b10000 '
b100 &
#365000
1#
#370000
0#
#372000
b11000110110111111001100110001101 !
b11000110110111111001100110001101 )
b10100 "
b10100 '
b101 &
#375000
1#
#380000
0#
#382000
b110010110000101000010001100101 !
b110010110000101000010001100101 )
b11000 "
b11000 '
b110 &
#385000
1#
#390000
0#
#392000
b1001001101110101001000010010 !
b1001001101110101001000010010 )
b11100 "
b11100 '
b111 &
#395000
1#
#400000
0#
#402000
b10000000111100111110001100000001 !
b10000000111100111110001100000001 )
b100000 "
b100000 '
b1000 &
#405000
1#
#410000
0#
#412000
b10000110110101111100110100001101 !
b10000110110101111100110100001101 )
b100100 "
b100100 '
b1001 &
#415000
1#
#420000
0#
#422000
b10111011001000111111000101110110 !
b10111011001000111111000101110110 )
b101000 "
b101000 '
b1010 &
#425000
1#
#430000
0#
#432000
b10011110100011011100110100111101 !
b10011110100011011100110100111101 )
b101100 "
b101100 '
b1011 &
#435000
1#
#440000
0#
#442000
b11110110110101000101011111101101 !
b11110110110101000101011111101101 )
b110000 "
b110000 '
b1100 &
#445000
1#
#450000
0#
#452000
b11000110001011011111011110001100 !
b11000110001011011111011110001100 )
b110100 "
b110100 '
b1101 &
#455000
1#
#460000
0#
#462000
b11111100111111011110100111111001 !
b11111100111111011110100111111001 )
b111000 "
b111000 '
b1110 &
#465000
1#
#470000
0#
#472000
b1100011001101110010010011000110 !
b1100011001101110010010011000110 )
b111100 "
b111100 '
b1111 &
#475000
1#
#480000
0#
#482000
b1100010111101111000010011000101 !
b1100010111101111000010011000101 )
b1000000 "
b1000000 '
b10000 &
#485000
1#
#490000
0#
#492000
b1010101000100111101001010101010 !
b1010101000100111101001010101010 )
b1000100 "
b1000100 '
b10001 &
